{"nodes": [{"id": "home_sciotti_code_spaceborne_spaceborne_cosmo_lib_py", "label": "cosmo_lib.py", "file_type": "code", "source_file": "spaceborne/cosmo_lib.py", "source_location": "L1"}, {"id": "spaceborne_cosmo_lib_cloelib_to_spaceborne_params_mapping", "label": "cloelib_to_spaceborne_params_mapping()", "file_type": "code", "source_file": "spaceborne/cosmo_lib.py", "source_location": "L28"}, {"id": "spaceborne_cosmo_lib_map_keys", "label": "map_keys()", "file_type": "code", "source_file": "spaceborne/cosmo_lib.py", "source_location": "L73"}, {"id": "spaceborne_cosmo_lib_ccl_comoving_distance", "label": "ccl_comoving_distance()", "file_type": "code", "source_file": "spaceborne/cosmo_lib.py", "source_location": "L118"}, {"id": "spaceborne_cosmo_lib_k_limber", "label": "k_limber()", "file_type": "code", "source_file": "spaceborne/cosmo_lib.py", "source_location": "L128"}, {"id": "spaceborne_cosmo_lib_get_kmax_limber", "label": "get_kmax_limber()", "file_type": "code", "source_file": "spaceborne/cosmo_lib.py", "source_location": "L142"}, {"id": "spaceborne_cosmo_lib_pk_from_ccl", "label": "pk_from_ccl()", "file_type": "code", "source_file": "spaceborne/cosmo_lib.py", "source_location": "L151"}, {"id": "spaceborne_cosmo_lib_z_to_a", "label": "z_to_a()", "file_type": "code", "source_file": "spaceborne/cosmo_lib.py", "source_location": "L177"}, {"id": "spaceborne_cosmo_lib_a_to_z", "label": "a_to_z()", "file_type": "code", "source_file": "spaceborne/cosmo_lib.py", "source_location": "L187"}, {"id": "spaceborne_cosmo_lib_growth_factor_ccl", "label": "growth_factor_ccl()", "file_type": "code", "source_file": "spaceborne/cosmo_lib.py", "source_location": "L191"}, {"id": "spaceborne_cosmo_lib_deg2_to_fsky", "label": "deg2_to_fsky()", "file_type": "code", "source_file": "spaceborne/cosmo_lib.py", "source_location": "L195"}, {"id": "spaceborne_cosmo_lib_fsky_to_deg2", "label": "fsky_to_deg2()", "file_type": "code", "source_file": "spaceborne/cosmo_lib.py", "source_location": "L200"}, {"id": "spaceborne_cosmo_lib_cl_integral_prefactor", "label": "cl_integral_prefactor()", "file_type": "code", "source_file": "spaceborne/cosmo_lib.py", "source_location": "L204"}, {"id": "spaceborne_cosmo_lib_get_omega_nu0", "label": "get_omega_nu0()", "file_type": "code", "source_file": "spaceborne/cosmo_lib.py", "source_location": "L252"}, {"id": "spaceborne_cosmo_lib_get_omega_nu0_new", "label": "get_omega_nu0_new()", "file_type": "code", "source_file": "spaceborne/cosmo_lib.py", "source_location": "L280"}, {"id": "spaceborne_cosmo_lib_get_omega_k0", "label": "get_omega_k0()", "file_type": "code", "source_file": "spaceborne/cosmo_lib.py", "source_location": "L309"}, {"id": "spaceborne_cosmo_lib_instantiate_cosmo_ccl_obj", "label": "instantiate_cosmo_ccl_obj()", "file_type": "code", "source_file": "spaceborne/cosmo_lib.py", "source_location": "L321"}, {"id": "spaceborne_cosmo_lib_project_pk", "label": "project_pk()", "file_type": "code", "source_file": "spaceborne/cosmo_lib.py", "source_location": "L371"}, {"id": "spaceborne_cosmo_lib_ell_prefactor_gamma_and_ia", "label": "ell_prefactor_gamma_and_ia()", "file_type": "code", "source_file": "spaceborne/cosmo_lib.py", "source_location": "L424"}, {"id": "spaceborne_cosmo_lib_ell_prefactor_mag", "label": "ell_prefactor_mag()", "file_type": "code", "source_file": "spaceborne/cosmo_lib.py", "source_location": "L433"}, {"id": "spaceborne_cosmo_lib_reshape_pk_vincenzo_to_2d", "label": "reshape_pk_vincenzo_to_2d()", "file_type": "code", "source_file": "spaceborne/cosmo_lib.py", "source_location": "L438"}, {"id": "spaceborne_cosmo_lib_sigma8_to_as", "label": "sigma8_to_As()", "file_type": "code", "source_file": "spaceborne/cosmo_lib.py", "source_location": "L447"}, {"id": "spaceborne_cosmo_lib_rationale_31", "label": "Maps cosmological parameters from the cloelib basis to the Spaceborne one.     R", "file_type": "rationale", "source_file": "spaceborne/cosmo_lib.py", "source_location": "L31"}, {"id": "spaceborne_cosmo_lib_rationale_74", "label": "Maps the keys of a dictionary based on a given key mapping, while retaining", "file_type": "rationale", "source_file": "spaceborne/cosmo_lib.py", "source_location": "L74"}, {"id": "spaceborne_cosmo_lib_rationale_129", "label": "This function is vectorized in ell OR z, but not both at the same time.     To v", "file_type": "rationale", "source_file": "spaceborne/cosmo_lib.py", "source_location": "L129"}, {"id": "spaceborne_cosmo_lib_rationale_143", "label": "Returns the maximum k_limber value for a given ell_grid and z_grid", "file_type": "rationale", "source_file": "spaceborne/cosmo_lib.py", "source_location": "L143"}, {"id": "spaceborne_cosmo_lib_rationale_152", "label": "! * the input k_array must be in 1/Mpc * .     If use_h_units is True, the outpu", "file_type": "rationale", "source_file": "spaceborne/cosmo_lib.py", "source_location": "L152"}, {"id": "spaceborne_cosmo_lib_rationale_205", "label": "r\"\"\"This is the integration \"prefactor\" for the cl integral, without the dz,", "file_type": "rationale", "source_file": "spaceborne/cosmo_lib.py", "source_location": "L205"}, {"id": "spaceborne_cosmo_lib_rationale_253", "label": "Calculate the neutrino mass density parameter (Omega_nu h^2).     Look in https:", "file_type": "rationale", "source_file": "spaceborne/cosmo_lib.py", "source_location": "L253"}, {"id": "spaceborne_cosmo_lib_rationale_281", "label": "Compute present-day neutrino density parameter \u03a9_\u03bd\u2080 (dimensionless).      \u03a9_\u03bd\u2080 =", "file_type": "rationale", "source_file": "spaceborne/cosmo_lib.py", "source_location": "L281"}, {"id": "spaceborne_cosmo_lib_rationale_381", "label": "Project the pk to get the cls, or the pk responses to get the projected response", "file_type": "rationale", "source_file": "spaceborne/cosmo_lib.py", "source_location": "L381"}, {"id": "spaceborne_cosmo_lib_rationale_425", "label": "From Kilbinger, M., Heymans, C., Asgari, M., et al. 2017, MNRAS, 472, 2126.", "file_type": "rationale", "source_file": "spaceborne/cosmo_lib.py", "source_location": "L425"}, {"id": "spaceborne_cosmo_lib_rationale_448", "label": "This function has been written by Matteo Martinelli", "file_type": "rationale", "source_file": "spaceborne/cosmo_lib.py", "source_location": "L448"}], "edges": [{"source": "home_sciotti_code_spaceborne_spaceborne_cosmo_lib_py", "target": "time", "relation": "imports", "context": "import", "confidence": "EXTRACTED", "source_file": "spaceborne/cosmo_lib.py", "source_location": "L1", "weight": 1.0}, {"source": "home_sciotti_code_spaceborne_spaceborne_cosmo_lib_py", "target": "warnings", "relation": "imports", "context": "import", "confidence": "EXTRACTED", "source_file": "spaceborne/cosmo_lib.py", "source_location": "L2", "weight": 1.0}, {"source": "home_sciotti_code_spaceborne_spaceborne_cosmo_lib_py", "target": "copy", "relation": "imports_from", "context": "import", "confidence": "EXTRACTED", "source_file": "spaceborne/cosmo_lib.py", "source_location": "L3", "weight": 1.0}, {"source": "home_sciotti_code_spaceborne_spaceborne_cosmo_lib_py", "target": "numpy", "relation": "imports", "context": "import", "confidence": "EXTRACTED", "source_file": "spaceborne/cosmo_lib.py", "source_location": "L5", "weight": 1.0}, {"source": "home_sciotti_code_spaceborne_spaceborne_cosmo_lib_py", "target": "pyccl", "relation": "imports", "context": "import", "confidence": "EXTRACTED", "source_file": "spaceborne/cosmo_lib.py", "source_location": "L6", "weight": 1.0}, {"source": "home_sciotti_code_spaceborne_spaceborne_cosmo_lib_py", "target": "scipy_integrate", "relation": "imports_from", "context": "import", "confidence": "EXTRACTED", "source_file": "spaceborne/cosmo_lib.py", "source_location": "L7", "weight": 1.0}, {"source": "home_sciotti_code_spaceborne_spaceborne_cosmo_lib_py", "target": "spaceborne", "relation": "imports_from", "context": "import", "confidence": "EXTRACTED", "source_file": "spaceborne/cosmo_lib.py", "source_location": "L9", "weight": 1.0}, {"source": "home_sciotti_code_spaceborne_spaceborne_cosmo_lib_py", "target": "spaceborne", "relation": "imports_from", "context": "import", "confidence": "EXTRACTED", "source_file": "spaceborne/cosmo_lib.py", "source_location": "L10", "weight": 1.0}, {"source": "home_sciotti_code_spaceborne_spaceborne_cosmo_lib_py", "target": "spaceborne_cosmo_lib_cloelib_to_spaceborne_params_mapping", "relation": "contains", "confidence": "EXTRACTED", "source_file": "spaceborne/cosmo_lib.py", "source_location": "L28", "weight": 1.0}, {"source": "home_sciotti_code_spaceborne_spaceborne_cosmo_lib_py", "target": "spaceborne_cosmo_lib_map_keys", "relation": "contains", "confidence": "EXTRACTED", "source_file": "spaceborne/cosmo_lib.py", "source_location": "L73", "weight": 1.0}, {"source": "home_sciotti_code_spaceborne_spaceborne_cosmo_lib_py", "target": "spaceborne_cosmo_lib_ccl_comoving_distance", "relation": "contains", "confidence": "EXTRACTED", "source_file": "spaceborne/cosmo_lib.py", "source_location": "L118", "weight": 1.0}, {"source": "home_sciotti_code_spaceborne_spaceborne_cosmo_lib_py", "target": "spaceborne_cosmo_lib_k_limber", "relation": "contains", "confidence": "EXTRACTED", "source_file": "spaceborne/cosmo_lib.py", "source_location": "L128", "weight": 1.0}, {"source": "home_sciotti_code_spaceborne_spaceborne_cosmo_lib_py", "target": "spaceborne_cosmo_lib_get_kmax_limber", "relation": "contains", "confidence": "EXTRACTED", "source_file": "spaceborne/cosmo_lib.py", "source_location": "L142", "weight": 1.0}, {"source": "home_sciotti_code_spaceborne_spaceborne_cosmo_lib_py", "target": "spaceborne_cosmo_lib_pk_from_ccl", "relation": "contains", "confidence": "EXTRACTED", "source_file": "spaceborne/cosmo_lib.py", "source_location": "L151", "weight": 1.0}, {"source": "home_sciotti_code_spaceborne_spaceborne_cosmo_lib_py", "target": "spaceborne_cosmo_lib_z_to_a", "relation": "contains", "confidence": "EXTRACTED", "source_file": "spaceborne/cosmo_lib.py", "source_location": "L177", "weight": 1.0}, {"source": "home_sciotti_code_spaceborne_spaceborne_cosmo_lib_py", "target": "spaceborne_cosmo_lib_a_to_z", "relation": "contains", "confidence": "EXTRACTED", "source_file": "spaceborne/cosmo_lib.py", "source_location": "L187", "weight": 1.0}, {"source": "home_sciotti_code_spaceborne_spaceborne_cosmo_lib_py", "target": "spaceborne_cosmo_lib_growth_factor_ccl", "relation": "contains", "confidence": "EXTRACTED", "source_file": "spaceborne/cosmo_lib.py", "source_location": "L191", "weight": 1.0}, {"source": "home_sciotti_code_spaceborne_spaceborne_cosmo_lib_py", "target": "spaceborne_cosmo_lib_deg2_to_fsky", "relation": "contains", "confidence": "EXTRACTED", "source_file": "spaceborne/cosmo_lib.py", "source_location": "L195", "weight": 1.0}, {"source": "home_sciotti_code_spaceborne_spaceborne_cosmo_lib_py", "target": "spaceborne_cosmo_lib_fsky_to_deg2", "relation": "contains", "confidence": "EXTRACTED", "source_file": "spaceborne/cosmo_lib.py", "source_location": "L200", "weight": 1.0}, {"source": "home_sciotti_code_spaceborne_spaceborne_cosmo_lib_py", "target": "spaceborne_cosmo_lib_cl_integral_prefactor", "relation": "contains", "confidence": "EXTRACTED", "source_file": "spaceborne/cosmo_lib.py", "source_location": "L204", "weight": 1.0}, {"source": "home_sciotti_code_spaceborne_spaceborne_cosmo_lib_py", "target": "spaceborne_cosmo_lib_get_omega_nu0", "relation": "contains", "confidence": "EXTRACTED", "source_file": "spaceborne/cosmo_lib.py", "source_location": "L252", "weight": 1.0}, {"source": "home_sciotti_code_spaceborne_spaceborne_cosmo_lib_py", "target": "spaceborne_cosmo_lib_get_omega_nu0_new", "relation": "contains", "confidence": "EXTRACTED", "source_file": "spaceborne/cosmo_lib.py", "source_location": "L280", "weight": 1.0}, {"source": "home_sciotti_code_spaceborne_spaceborne_cosmo_lib_py", "target": "spaceborne_cosmo_lib_get_omega_k0", "relation": "contains", "confidence": "EXTRACTED", "source_file": "spaceborne/cosmo_lib.py", "source_location": "L309", "weight": 1.0}, {"source": "home_sciotti_code_spaceborne_spaceborne_cosmo_lib_py", "target": "spaceborne_cosmo_lib_instantiate_cosmo_ccl_obj", "relation": "contains", "confidence": "EXTRACTED", "source_file": "spaceborne/cosmo_lib.py", "source_location": "L321", "weight": 1.0}, {"source": "home_sciotti_code_spaceborne_spaceborne_cosmo_lib_py", "target": "spaceborne_cosmo_lib_project_pk", "relation": "contains", "confidence": "EXTRACTED", "source_file": "spaceborne/cosmo_lib.py", "source_location": "L371", "weight": 1.0}, {"source": "home_sciotti_code_spaceborne_spaceborne_cosmo_lib_py", "target": "spaceborne_cosmo_lib_ell_prefactor_gamma_and_ia", "relation": "contains", "confidence": "EXTRACTED", "source_file": "spaceborne/cosmo_lib.py", "source_location": "L424", "weight": 1.0}, {"source": "home_sciotti_code_spaceborne_spaceborne_cosmo_lib_py", "target": "spaceborne_cosmo_lib_ell_prefactor_mag", "relation": "contains", "confidence": "EXTRACTED", "source_file": "spaceborne/cosmo_lib.py", "source_location": "L433", "weight": 1.0}, {"source": "home_sciotti_code_spaceborne_spaceborne_cosmo_lib_py", "target": "spaceborne_cosmo_lib_reshape_pk_vincenzo_to_2d", "relation": "contains", "confidence": "EXTRACTED", "source_file": "spaceborne/cosmo_lib.py", "source_location": "L438", "weight": 1.0}, {"source": "home_sciotti_code_spaceborne_spaceborne_cosmo_lib_py", "target": "spaceborne_cosmo_lib_sigma8_to_as", "relation": "contains", "confidence": "EXTRACTED", "source_file": "spaceborne/cosmo_lib.py", "source_location": "L447", "weight": 1.0}, {"source": "spaceborne_cosmo_lib_ccl_comoving_distance", "target": "spaceborne_cosmo_lib_z_to_a", "relation": "calls", "context": "call", "confidence": "EXTRACTED", "source_file": "spaceborne/cosmo_lib.py", "source_location": "L119", "weight": 1.0}, {"source": "spaceborne_cosmo_lib_k_limber", "target": "spaceborne_cosmo_lib_ccl_comoving_distance", "relation": "calls", "context": "call", "confidence": "EXTRACTED", "source_file": "spaceborne/cosmo_lib.py", "source_location": "L139", "weight": 1.0}, {"source": "spaceborne_cosmo_lib_get_kmax_limber", "target": "spaceborne_cosmo_lib_k_limber", "relation": "calls", "context": "call", "confidence": "EXTRACTED", "source_file": "spaceborne/cosmo_lib.py", "source_location": "L147", "weight": 1.0}, {"source": "spaceborne_cosmo_lib_growth_factor_ccl", "target": "spaceborne_cosmo_lib_z_to_a", "relation": "calls", "context": "call", "confidence": "EXTRACTED", "source_file": "spaceborne/cosmo_lib.py", "source_location": "L192", "weight": 1.0}, {"source": "spaceborne_cosmo_lib_cl_integral_prefactor", "target": "spaceborne_cosmo_lib_ccl_comoving_distance", "relation": "calls", "context": "call", "confidence": "EXTRACTED", "source_file": "spaceborne/cosmo_lib.py", "source_location": "L230", "weight": 1.0}, {"source": "spaceborne_cosmo_lib_cl_integral_prefactor", "target": "spaceborne_cosmo_lib_z_to_a", "relation": "calls", "context": "call", "confidence": "EXTRACTED", "source_file": "spaceborne/cosmo_lib.py", "source_location": "L231", "weight": 1.0}, {"source": "spaceborne_cosmo_lib_instantiate_cosmo_ccl_obj", "target": "spaceborne_cosmo_lib_get_omega_nu0", "relation": "calls", "context": "call", "confidence": "EXTRACTED", "source_file": "spaceborne/cosmo_lib.py", "source_location": "L329", "weight": 1.0}, {"source": "spaceborne_cosmo_lib_instantiate_cosmo_ccl_obj", "target": "spaceborne_cosmo_lib_get_omega_k0", "relation": "calls", "context": "call", "confidence": "EXTRACTED", "source_file": "spaceborne/cosmo_lib.py", "source_location": "L339", "weight": 1.0}, {"source": "spaceborne_cosmo_lib_project_pk", "target": "spaceborne_cosmo_lib_cl_integral_prefactor", "relation": "calls", "context": "call", "confidence": "EXTRACTED", "source_file": "spaceborne/cosmo_lib.py", "source_location": "L391", "weight": 1.0}, {"source": "spaceborne_cosmo_lib_project_pk", "target": "spaceborne_cosmo_lib_k_limber", "relation": "calls", "context": "call", "confidence": "EXTRACTED", "source_file": "spaceborne/cosmo_lib.py", "source_location": "L407", "weight": 1.0}, {"source": "spaceborne_cosmo_lib_rationale_31", "target": "spaceborne_cosmo_lib_cloelib_to_spaceborne_params_mapping", "relation": "rationale_for", "confidence": "EXTRACTED", "source_file": "spaceborne/cosmo_lib.py", "source_location": "L31", "weight": 1.0}, {"source": "spaceborne_cosmo_lib_rationale_74", "target": "spaceborne_cosmo_lib_map_keys", "relation": "rationale_for", "confidence": "EXTRACTED", "source_file": "spaceborne/cosmo_lib.py", "source_location": "L74", "weight": 1.0}, {"source": "spaceborne_cosmo_lib_rationale_129", "target": "spaceborne_cosmo_lib_k_limber", "relation": "rationale_for", "confidence": "EXTRACTED", "source_file": "spaceborne/cosmo_lib.py", "source_location": "L129", "weight": 1.0}, {"source": "spaceborne_cosmo_lib_rationale_143", "target": "spaceborne_cosmo_lib_get_kmax_limber", "relation": "rationale_for", "confidence": "EXTRACTED", "source_file": "spaceborne/cosmo_lib.py", "source_location": "L143", "weight": 1.0}, {"source": "spaceborne_cosmo_lib_rationale_152", "target": "spaceborne_cosmo_lib_pk_from_ccl", "relation": "rationale_for", "confidence": "EXTRACTED", "source_file": "spaceborne/cosmo_lib.py", "source_location": "L152", "weight": 1.0}, {"source": "spaceborne_cosmo_lib_rationale_205", "target": "spaceborne_cosmo_lib_cl_integral_prefactor", "relation": "rationale_for", "confidence": "EXTRACTED", "source_file": "spaceborne/cosmo_lib.py", "source_location": "L205", "weight": 1.0}, {"source": "spaceborne_cosmo_lib_rationale_253", "target": "spaceborne_cosmo_lib_get_omega_nu0", "relation": "rationale_for", "confidence": "EXTRACTED", "source_file": "spaceborne/cosmo_lib.py", "source_location": "L253", "weight": 1.0}, {"source": "spaceborne_cosmo_lib_rationale_281", "target": "spaceborne_cosmo_lib_get_omega_nu0_new", "relation": "rationale_for", "confidence": "EXTRACTED", "source_file": "spaceborne/cosmo_lib.py", "source_location": "L281", "weight": 1.0}, {"source": "spaceborne_cosmo_lib_rationale_381", "target": "spaceborne_cosmo_lib_project_pk", "relation": "rationale_for", "confidence": "EXTRACTED", "source_file": "spaceborne/cosmo_lib.py", "source_location": "L381", "weight": 1.0}, {"source": "spaceborne_cosmo_lib_rationale_425", "target": "spaceborne_cosmo_lib_ell_prefactor_gamma_and_ia", "relation": "rationale_for", "confidence": "EXTRACTED", "source_file": "spaceborne/cosmo_lib.py", "source_location": "L425", "weight": 1.0}, {"source": "spaceborne_cosmo_lib_rationale_448", "target": "spaceborne_cosmo_lib_sigma8_to_as", "relation": "rationale_for", "confidence": "EXTRACTED", "source_file": "spaceborne/cosmo_lib.py", "source_location": "L448", "weight": 1.0}], "raw_calls": [{"caller_nid": "spaceborne_cosmo_lib_cloelib_to_spaceborne_params_mapping", "callee": "As_to_sigma8_max_precision", "is_member_call": true, "source_file": "/home/sciotti/code/Spaceborne/spaceborne/cosmo_lib.py", "source_location": "L41", "receiver": null}, {"caller_nid": "spaceborne_cosmo_lib_map_keys", "callee": "items", "is_member_call": true, "source_file": "/home/sciotti/code/Spaceborne/spaceborne/cosmo_lib.py", "source_location": "L108", "receiver": null}, {"caller_nid": "spaceborne_cosmo_lib_map_keys", "callee": "keys", "is_member_call": true, "source_file": "/home/sciotti/code/Spaceborne/spaceborne/cosmo_lib.py", "source_location": "L112", "receiver": null}, {"caller_nid": "spaceborne_cosmo_lib_map_keys", "callee": "keys", "is_member_call": true, "source_file": "/home/sciotti/code/Spaceborne/spaceborne/cosmo_lib.py", "source_location": "L112", "receiver": null}, {"caller_nid": "spaceborne_cosmo_lib_ccl_comoving_distance", "callee": "comoving_radial_distance", "is_member_call": true, "source_file": "/home/sciotti/code/Spaceborne/spaceborne/cosmo_lib.py", "source_location": "L122", "receiver": null}, {"caller_nid": "spaceborne_cosmo_lib_ccl_comoving_distance", "callee": "comoving_radial_distance", "is_member_call": true, "source_file": "/home/sciotti/code/Spaceborne/spaceborne/cosmo_lib.py", "source_location": "L125", "receiver": null}, {"caller_nid": "spaceborne_cosmo_lib_get_kmax_limber", "callee": "atleast_1d", "is_member_call": true, "source_file": "/home/sciotti/code/Spaceborne/spaceborne/cosmo_lib.py", "source_location": "L145", "receiver": null}, {"caller_nid": "spaceborne_cosmo_lib_get_kmax_limber", "callee": "append", "is_member_call": true, "source_file": "/home/sciotti/code/Spaceborne/spaceborne/cosmo_lib.py", "source_location": "L147", "receiver": null}, {"caller_nid": "spaceborne_cosmo_lib_pk_from_ccl", "callee": "ValueError", "is_member_call": false, "source_file": "/home/sciotti/code/Spaceborne/spaceborne/cosmo_lib.py", "source_location": "L162", "receiver": null}, {"caller_nid": "spaceborne_cosmo_lib_pk_from_ccl", "callee": "atleast_1d", "is_member_call": true, "source_file": "/home/sciotti/code/Spaceborne/spaceborne/cosmo_lib.py", "source_location": "L164", "receiver": null}, {"caller_nid": "spaceborne_cosmo_lib_pk_from_ccl", "callee": "array", "is_member_call": true, "source_file": "/home/sciotti/code/Spaceborne/spaceborne/cosmo_lib.py", "source_location": "L165", "receiver": null}, {"caller_nid": "spaceborne_cosmo_lib_pk_from_ccl", "callee": "ccl_pk_func", "is_member_call": false, "source_file": "/home/sciotti/code/Spaceborne/spaceborne/cosmo_lib.py", "source_location": "L166", "receiver": null}, {"caller_nid": "spaceborne_cosmo_lib_growth_factor_ccl", "callee": "growth_factor", "is_member_call": true, "source_file": "/home/sciotti/code/Spaceborne/spaceborne/cosmo_lib.py", "source_location": "L192", "receiver": null}, {"caller_nid": "spaceborne_cosmo_lib_cl_integral_prefactor", "callee": "h_over_h0", "is_member_call": true, "source_file": "/home/sciotti/code/Spaceborne/spaceborne/cosmo_lib.py", "source_location": "L232", "receiver": null}, {"caller_nid": "spaceborne_cosmo_lib_cl_integral_prefactor", "callee": "ValueError", "is_member_call": false, "source_file": "/home/sciotti/code/Spaceborne/spaceborne/cosmo_lib.py", "source_location": "L237", "receiver": null}, {"caller_nid": "spaceborne_cosmo_lib_cl_integral_prefactor", "callee": "ValueError", "is_member_call": false, "source_file": "/home/sciotti/code/Spaceborne/spaceborne/cosmo_lib.py", "source_location": "L248", "receiver": null}, {"caller_nid": "spaceborne_cosmo_lib_get_omega_k0", "callee": "warn", "is_member_call": true, "source_file": "/home/sciotti/code/Spaceborne/spaceborne/cosmo_lib.py", "source_location": "L312", "receiver": null}, {"caller_nid": "spaceborne_cosmo_lib_instantiate_cosmo_ccl_obj", "callee": "flatten_dict", "is_member_call": true, "source_file": "/home/sciotti/code/Spaceborne/spaceborne/cosmo_lib.py", "source_location": "L327", "receiver": null}, {"caller_nid": "spaceborne_cosmo_lib_instantiate_cosmo_ccl_obj", "callee": "Cosmology", "is_member_call": true, "source_file": "/home/sciotti/code/Spaceborne/spaceborne/cosmo_lib.py", "source_location": "L352", "receiver": null}, {"caller_nid": "spaceborne_cosmo_lib_project_pk", "callee": "einsum", "is_member_call": true, "source_file": "/home/sciotti/code/Spaceborne/spaceborne/cosmo_lib.py", "source_location": "L396", "receiver": null}, {"caller_nid": "spaceborne_cosmo_lib_project_pk", "callee": "zeros", "is_member_call": true, "source_file": "/home/sciotti/code/Spaceborne/spaceborne/cosmo_lib.py", "source_location": "L401", "receiver": null}, {"caller_nid": "spaceborne_cosmo_lib_project_pk", "callee": "time", "is_member_call": true, "source_file": "/home/sciotti/code/Spaceborne/spaceborne/cosmo_lib.py", "source_location": "L404", "receiver": null}, {"caller_nid": "spaceborne_cosmo_lib_project_pk", "callee": "pab_k_z_interp_func", "is_member_call": false, "source_file": "/home/sciotti/code/Spaceborne/spaceborne/cosmo_lib.py", "source_location": "L412", "receiver": null}, {"caller_nid": "spaceborne_cosmo_lib_project_pk", "callee": "einsum", "is_member_call": true, "source_file": "/home/sciotti/code/Spaceborne/spaceborne/cosmo_lib.py", "source_location": "L415", "receiver": null}, {"caller_nid": "spaceborne_cosmo_lib_project_pk", "callee": "simps", "is_member_call": false, "source_file": "/home/sciotti/code/Spaceborne/spaceborne/cosmo_lib.py", "source_location": "L418", "receiver": null}, {"caller_nid": "spaceborne_cosmo_lib_project_pk", "callee": "time", "is_member_call": true, "source_file": "/home/sciotti/code/Spaceborne/spaceborne/cosmo_lib.py", "source_location": "L420", "receiver": null}, {"caller_nid": "spaceborne_cosmo_lib_ell_prefactor_gamma_and_ia", "callee": "sqrt", "is_member_call": true, "source_file": "/home/sciotti/code/Spaceborne/spaceborne/cosmo_lib.py", "source_location": "L429", "receiver": null}, {"caller_nid": "spaceborne_cosmo_lib_reshape_pk_vincenzo_to_2d", "callee": "genfromtxt", "is_member_call": true, "source_file": "/home/sciotti/code/Spaceborne/spaceborne/cosmo_lib.py", "source_location": "L440", "receiver": null}, {"caller_nid": "spaceborne_cosmo_lib_reshape_pk_vincenzo_to_2d", "callee": "unique", "is_member_call": true, "source_file": "/home/sciotti/code/Spaceborne/spaceborne/cosmo_lib.py", "source_location": "L441", "receiver": null}, {"caller_nid": "spaceborne_cosmo_lib_reshape_pk_vincenzo_to_2d", "callee": "unique", "is_member_call": true, "source_file": "/home/sciotti/code/Spaceborne/spaceborne/cosmo_lib.py", "source_location": "L442", "receiver": null}, {"caller_nid": "spaceborne_cosmo_lib_reshape_pk_vincenzo_to_2d", "callee": "reshape", "is_member_call": true, "source_file": "/home/sciotti/code/Spaceborne/spaceborne/cosmo_lib.py", "source_location": "L443", "receiver": null}, {"caller_nid": "spaceborne_cosmo_lib_sigma8_to_as", "callee": "deepcopy", "is_member_call": false, "source_file": "/home/sciotti/code/Spaceborne/spaceborne/cosmo_lib.py", "source_location": "L451", "receiver": null}, {"caller_nid": "spaceborne_cosmo_lib_sigma8_to_as", "callee": "update", "is_member_call": true, "source_file": "/home/sciotti/code/Spaceborne/spaceborne/cosmo_lib.py", "source_location": "L463", "receiver": null}, {"caller_nid": "spaceborne_cosmo_lib_sigma8_to_as", "callee": "set_params", "is_member_call": true, "source_file": "/home/sciotti/code/Spaceborne/spaceborne/cosmo_lib.py", "source_location": "L464", "receiver": null}, {"caller_nid": "spaceborne_cosmo_lib_sigma8_to_as", "callee": "items", "is_member_call": true, "source_file": "/home/sciotti/code/Spaceborne/spaceborne/cosmo_lib.py", "source_location": "L465", "receiver": null}, {"caller_nid": "spaceborne_cosmo_lib_sigma8_to_as", "callee": "set_matter_power", "is_member_call": true, "source_file": "/home/sciotti/code/Spaceborne/spaceborne/cosmo_lib.py", "source_location": "L467", "receiver": null}, {"caller_nid": "spaceborne_cosmo_lib_sigma8_to_as", "callee": "get_results", "is_member_call": true, "source_file": "/home/sciotti/code/Spaceborne/spaceborne/cosmo_lib.py", "source_location": "L468", "receiver": null}, {"caller_nid": "spaceborne_cosmo_lib_sigma8_to_as", "callee": "array", "is_member_call": true, "source_file": "/home/sciotti/code/Spaceborne/spaceborne/cosmo_lib.py", "source_location": "L469", "receiver": null}, {"caller_nid": "spaceborne_cosmo_lib_sigma8_to_as", "callee": "get_sigma8", "is_member_call": true, "source_file": "/home/sciotti/code/Spaceborne/spaceborne/cosmo_lib.py", "source_location": "L469", "receiver": null}]}