{"nodes": [{"id": "spaceborne_cosmo_lib", "label": "spaceborne/cosmo_lib.py", "file_type": "code", "source_file": "spaceborne/cosmo_lib.py"}, {"id": "cosmo_lib_pk_from_ccl", "label": "pk_from_ccl", "file_type": "concept", "source_file": "spaceborne/cosmo_lib.py", "source_location": null, "source_url": null, "captured_at": null, "author": null, "contributor": null}, {"id": "cosmo_lib_z_to_a", "label": "z_to_a", "file_type": "concept", "source_file": "spaceborne/cosmo_lib.py", "source_location": null, "source_url": null, "captured_at": null, "author": null, "contributor": null}], "edges": [], "hyperedges": []}