{"nodes": [{"id": "wf_cl_lib_compute_cls_or_interpolate_input_cls", "label": "compute_cls_or_interpolate_input_cls", "file_type": "code", "source_file": "spaceborne/wf_cl_lib.py", "source_location": null, "source_url": null, "captured_at": null, "author": null, "contributor": null}, {"id": "wf_cl_lib_convolve_nz_with_p_ph", "label": "convolve_nz_with_p_ph", "file_type": "code", "source_file": "spaceborne/wf_cl_lib.py", "source_location": null, "source_url": null, "captured_at": null, "author": null, "contributor": null}, {"id": "wf_cl_lib_build_galaxy_bias_2d_arr", "label": "build_galaxy_bias_2d_arr", "file_type": "code", "source_file": "spaceborne/wf_cl_lib.py", "source_location": null, "source_url": null, "captured_at": null, "author": null, "contributor": null}, {"id": "wf_cl_lib_build_ia_bias_1d_arr", "label": "build_ia_bias_1d_arr", "file_type": "code", "source_file": "spaceborne/wf_cl_lib.py", "source_location": null, "source_url": null, "captured_at": null, "author": null, "contributor": null}, {"id": "wf_cl_lib_cl_ccl", "label": "cl_ccl", "file_type": "code", "source_file": "spaceborne/wf_cl_lib.py", "source_location": null, "source_url": null, "captured_at": null, "author": null, "contributor": null}], "edges": [{"source": "wf_cl_lib_compute_cls_or_interpolate_input_cls", "target": "sb_lib_build_cl_3x2pt_5d", "relation": "calls", "confidence": "EXTRACTED", "confidence_score": 1.0, "source_file": "spaceborne/wf_cl_lib.py", "source_location": null, "weight": 1.0}, {"source": "wf_cl_lib_cl_ccl", "target": "sb_lib_sum_split_g_terms_allprobeblocks_alldims", "relation": "conceptually_related_to", "confidence": "INFERRED", "confidence_score": 0.5, "source_file": "spaceborne/wf_cl_lib.py", "source_location": null, "weight": 1.0}], "hyperedges": []}